sigur_interact/__init__.py
sigur_interact/commands.py
sigur_interact/emulator.py
sigur_interact/functions.py
sigur_interact/main.py
sigur_interact/settings.py
sigur_interact/tests/__init__.py
sigur_interact/tests/main_test.py
sigur_interact/tests/make_connection_test.py
sigur_interact/tests/settings_test.py
sigur_interact/tests/functions_test/__init__.py
sigur_interact/tests/functions_test/get_object_info_test.py
sigur_interact/tests/functions_test/send_command_test.py
sigur_interact-1.6.dist-info/LICENSE
sigur_interact-1.6.dist-info/METADATA
sigur_interact-1.6.dist-info/WHEEL
sigur_interact-1.6.dist-info/top_level.txt
sigur_interact-1.6.dist-info/RECORD
